{"ch1.md":"CPT540yw","ch10.md":"DkdOYBfY","ch11.md":"BTQjtoUh","ch12.md":"Cl8QcaE4","ch13.md":"hzOSQUX8","ch14.md":"CtoQfTyo","ch15.md":"Bk9TGnd9","ch16.md":"4BfciF5s","ch17.md":"DcmTlbRj","ch18.md":"tdPRHWon","ch19.md":"BplHv05E","ch2.md":"BGCZ2eMW","ch20.md":"CuspFGwI","ch21.md":"CNTFqikp","ch22.md":"BGQfHVhI","ch23.md":"CzIbgVQR","ch24.md":"ChUJyo0G","ch25.md":"BjMjItvj","ch26.md":"PUX9q49O","ch27.md":"TUEMb1F6","ch28.md":"uB_DmXg0","ch29.md":"CjGjQrFa","ch3.md":"BMRBmQpU","ch30.md":"BirXMSUo","ch31.md":"C8ZfhxqS","ch32.md":"DchJqhTm","ch33.md":"xdwUxz1D","ch34.md":"DAcl5hg6","ch35.md":"9PqHzGn2","ch36.md":"BXKK_EAg","ch37.md":"jIyIig5G","ch38.md":"DP9qBDVT","ch39.md":"DtnPCbRr","ch4.md":"_OjC0X9l","ch5.md":"qJNEOAo2","ch6.md":"C708AVkH","ch7.md":"BFZRPCbD","ch8.md":"DVcu2UC6","ch9.md":"B1kuOcgQ","ch9b.md":"DtIC2b83","index.md":"v8esgNn_","part1.md":"DXWgXwzx","part2.md":"BKqhN7zF","part3.md":"e-XOsYYp","part4.md":"C2o84qbt","part5.md":"DMIeQvKf","part6.md":"BsDq5GUe","preface.md":"zzkRJeNO"}
